orijin_sdk/__init__.py
orijin_sdk/defaults.py
orijin_sdk/gql.py
orijin_sdk/types.py
orijin_sdk/auth/__init__.py
orijin_sdk/helpers/__init__.py
orijin_sdk/helpers/formatting.py
orijin_sdk/helpers/input_types.py
orijin_sdk/helpers/mutation_builder.py
orijin_sdk/helpers/query_builder.py
orijin_sdk/helpers/table_mapping.py
orijin_sdk-0.3.1.dist-info/METADATA
orijin_sdk-0.3.1.dist-info/WHEEL
orijin_sdk-0.3.1.dist-info/top_level.txt
orijin_sdk-0.3.1.dist-info/RECORD
