Metadata-Version: 2.1
Name: orijin-sdk
Version: 0.3.1
Summary: Orijin SDK for client development
Home-page: https://github.com/orijinplus/python-tools
Author: Orijin
Author-email: 
License: MIT
Requires-Dist: requests
